CHANGES
MANIFEST.in
README
setup.py
django_project_settings.egg-info/PKG-INFO
django_project_settings.egg-info/SOURCES.txt
django_project_settings.egg-info/dependency_links.txt
django_project_settings.egg-info/top_level.txt
docs/conf.py
docs/globals
docs/index.rst
docs/install.rst
project_settings/__init__.py
project_settings/__init__.pyc
project_settings/admin.py
project_settings/admin.pyc
project_settings/apps.py
project_settings/apps.pyc
project_settings/conf.py
project_settings/conf.pyc
project_settings/context_processors.py
project_settings/forms.py
project_settings/forms.pyc
project_settings/models.py
project_settings/models.pyc
project_settings/registry.py
project_settings/registry.pyc
project_settings/values.py
project_settings/values.pyc
project_settings/migrations/0001_initial.py
project_settings/migrations/0002_auto_20140912_1155.py
project_settings/migrations/0003_auto_20140915_0721.py
project_settings/migrations/__init__.py
project_settings/south_migrations/0001_initial.py
project_settings/south_migrations/__init__.py
project_settings/templates/admin/project_settings/setting/_change_list.html
project_settings/templates/admin/project_settings/setting/change_form.html
project_settings/templates/admin/project_settings/setting/change_list.html
tests/__init__.py
tests/conftest.py
tests/settings.py
tests/test_appsettings.py